Metadata-Version: 2.4
Name: sqlite-web
Version: 0.7.0
Summary: web-based sqlite database browser
Author-email: Charles Leifer <coleifer@gmail.com>
Project-URL: Repository, https://github.com/coleifer/sqlite-web
Classifier: Environment :: Web Environment
Classifier: Programming Language :: Python :: 3
Classifier: Topic :: Database
Classifier: Topic :: Database :: Front-Ends
Classifier: Topic :: Software Development :: Libraries :: Python Modules
License-File: LICENSE
Requires-Dist: flask
Requires-Dist: peewee>=3.0.0
Requires-Dist: pygments
Dynamic: license-file
